{
  "id": "tools",
  "title": "Tools Module",
  "cohesion": 0.85,
  "members": [
    "..."
  ],
  "filePaths": [
    "src/tools/"
  ],
  "generatedAt": "2026-03-24T20:24:05.656Z",
  "sections": {
    "_intro": "The tool system in this project is designed for modularity and efficient tool selection. Here's a breakdown of its key components and functionalities.\n\n### Tool Registration\n\nTools are defined and managed through a centralized system. The `src/codebuddy/tools.ts` file appears to be the main entry point for tool definitions and management, importing various modular tool definitions from `./tool-definitions/index.js`.\n\nThe `TOOL_METADATA` constant in `src/tools/metadata.ts` plays a crucial role in registering tools. It's an array of `ToolMetadata` objects, each containing:\n*   `name`: The unique name of the tool (e.g., `view_file`, `create_file`).\n*   `category`: The category the tool belongs to (e.g., `file_read`, `file_write`).\n*   `keywords`: A list of keywords associated with the tool, used for RAG selection.\n*   `priority`: A numerical value indicating the tool's priority.\n*   `description`: A brief description of what the tool does.\n\nThis metadata provides essential information for tool discovery and selection. The `getToolRegistry()` function (imported in `src/codebuddy/tools.ts`) is likely responsible for compiling and managing these registered tools.\n\n### Tool Categories\n\nThe tool system categorizes tools to facilitate better organization and selection. From the `src/tools/metadata.ts` file, we can infer several categories, including:\n\n*   `file_read`: For tools that read file contents or list directories (e.g., `view_file`, `list_directory`).\n*   `file_write`: For tools that create, modify, or delete files (e.g., `create_file`, `str_replace_editor`, `edit_file`, `multi_edit`).\n*   `search`: For tools that perform various search operations (e.g., `search`, `grep`, `web_search`, `search_multi`).\n*   `code_analysis`: For tools that analyze code (e.g., `bug_finder`).\n\nThe `src/codebuddy/tools.ts` file also imports various tool groups like `CORE_TOOLS`, `SEARCH_TOOLS`, `TODO_TOOLS`, `WEB_TOOLS`, `ADVANCED_TOOLS`, `BATCH_TOOLS`, and `GRAPH_TOOLS`, suggesting a broader categorization scheme.\n\n### RAG Selection (Retrieval-Augmented Generation)\n\nTool selection is a critical part of the system, enabling the agent to choose the most relevant tools for a given user query. The `src/codebuddy/tools.ts` file imports functions like `getToolSelector()` and `selectRelevantTools()` from `../tools/tool-selector.js`. This indicates a RAG-based approach where:\n\n1.  **Query Classification:** User queries are likely classified to understand their intent and identify relevant tool categories.\n2.  **Keyword Matching:** The `keywords` defined in `TOOL_METADATA` are used to match against the classified query.\n3.  **Tool Filtering:** `applyToolFilter()` (also imported in `src/codebuddy/tools.ts`) is used to refine the selection based on various criteria.\n4.  **Priority:** The `priority` field in `TOOL_METADATA` helps in ranking tools when multiple tools match a query.\n\nThis process ensures that the agent efficiently retrieves and selects the most appropriate tools to address the user's request.\n\n### Batch Execution\n\nThe `src/tools/batch-tool.ts` file describes a mechanism for executing multiple read-only tool calls in parallel. This significantly improves efficiency for operations that don't modify the codebase.\n\nKey aspects of batch execution include:\n\n*   **Parallel Execution:** Tools are executed concurrently using `Promise.allSettled()`.\n*   **Read-Only Tools:** A `READ_ONLY_TOOLS` set explicitly lists tools considered safe for parallel execution (e.g., `view_file`, `search`, `list_directory`, `web_search`, `codebase_map`, `code_graph`).\n*   **Destructive Tool Blocking:** A `DESTRUCTIVE_TOOLS` set lists tools that modify the codebase (e.g., `bash`, `create_file`, `edit_file`, `multi_edit`). These tools are blocked in non-YOLO (non-destructive) batch mode to prevent unintended changes.\n*   **Maximum Batch Size:** `MAX_BATCH_SIZE` is set to 25, limiting the number of tool calls in a single batch to prevent overwhelming the system.\n*   **Prevention of Recursive Batch Calls:** The system prevents nested batch calls to maintain control and avoid potential deadlocks or infinite loops.\n\nThis batch execution mechanism allows for faster processing of information-gathering tasks while maintaining safeguards against unintended modifications.\n\n### Bug Finder Tool\n\nThe `src/tools/bug-finder-tool.ts` file introduces a static analysis tool for detecting common bug patterns. This tool uses a regex-based approach across multiple languages (TypeScript, JavaScript, Python, Go, Rust, Java).\n\nKey features of the Bug Finder Tool:\n\n*   **Pattern-Based Detection:** It relies on `BugPattern` definitions, which include a `RegExp`, `severity` (critical, high, medium, low), `category` (e.g., null-access, unchecked-error, security, dead-code), `message`, `suggestion`, and `languages` it applies to.\n*   **Language Detection:** The `detectLanguage` function identifies the programming language based on file extensions.\n*   **Bug Reporting:** It generates `BugReport` objects, detailing the file, line number, severity, category, message, and a suggestion for remediation.\n\nThis tool demonstrates a specific application of the tool system for code quality and static analysis."
  }
}